create_fastapi_boilerplate/__init__.py
create_fastapi_boilerplate/__main__.py
create_fastapi_boilerplate/cli.py
create_fastapi_boilerplate/generator.py
create_fastapi_boilerplate-1.0.1.dist-info/licenses/LICENSE
create_fastapi_boilerplate-1.0.1.dist-info/METADATA
create_fastapi_boilerplate-1.0.1.dist-info/WHEEL
create_fastapi_boilerplate-1.0.1.dist-info/entry_points.txt
create_fastapi_boilerplate-1.0.1.dist-info/top_level.txt
create_fastapi_boilerplate-1.0.1.dist-info/RECORD
