Metadata-Version: 2.4
Name: create-fastapi-boilerplate
Version: 1.0.1
Summary: Production-grade FastAPI project generator with enterprise features
Author-email: Parth Joshi <parthjoshi.1618@gmail.com>
License: MIT
Project-URL: Homepage, https://github.com/parth1618/fastapi-boilerplate
Project-URL: Documentation, https://github.com/parth1618/fastapi-boilerplate#readme
Project-URL: Repository, https://github.com/parth1618/fastapi-boilerplate
Project-URL: Bug Tracker, https://github.com/parth1618/fastapi-boilerplate/issues
Keywords: fastapi,boilerplate,template,generator,cli,project-generator
Classifier: Development Status :: 5 - Production/Stable
Classifier: Intended Audience :: Developers
Classifier: Topic :: Software Development :: Code Generators
Classifier: License :: OSI Approved :: MIT License
Classifier: Programming Language :: Python :: 3
Classifier: Programming Language :: Python :: 3.9
Classifier: Programming Language :: Python :: 3.10
Classifier: Programming Language :: Python :: 3.11
Classifier: Programming Language :: Python :: 3.12
Classifier: Framework :: FastAPI
Classifier: Operating System :: OS Independent
Requires-Python: >=3.9
License-File: LICENSE
Provides-Extra: dev
Requires-Dist: pytest>=7.0; extra == "dev"
Requires-Dist: pytest-cov; extra == "dev"
Requires-Dist: pytest-mock; extra == "dev"
Dynamic: license-file
